pyfsntfs.cp39-win_amd64.pyd
libfsntfs_python-20251019.dist-info/METADATA
libfsntfs_python-20251019.dist-info/WHEEL
libfsntfs_python-20251019.dist-info/top_level.txt
libfsntfs_python-20251019.dist-info/RECORD
